tempenviron/__init__.py
tempenviron/tempenviron.py
tempenviron-0.0.1.dist-info/DESCRIPTION.rst
tempenviron-0.0.1.dist-info/METADATA
tempenviron-0.0.1.dist-info/RECORD
tempenviron-0.0.1.dist-info/WHEEL
tempenviron-0.0.1.dist-info/metadata.json
tempenviron-0.0.1.dist-info/top_level.txt
