Metadata-Version: 2.0
Name: tempenviron
Version: 0.0.1
Summary: Temporary modify your environment variables with context manager
Home-page: https://github.com/u1234x1234/tempenviron
Author: u1234x1234
Author-email: u1234x1234@gmail.com
License: MIT
Platform: UNKNOWN
Classifier: Programming Language :: Python :: 3
Classifier: Development Status :: 3 - Alpha
Classifier: Topic :: Utilities
Classifier: License :: OSI Approved :: MIT License
